CHANGES.txt
CONTRIBUTORS.txt
COPYRIGHT.txt
LICENSE.txt
MANIFEST.in
README.txt
TODO.txt
setup.cfg
setup.py
collective/__init__.py
collective.groupspace.roles.egg-info/PKG-INFO
collective.groupspace.roles.egg-info/SOURCES.txt
collective.groupspace.roles.egg-info/dependency_links.txt
collective.groupspace.roles.egg-info/entry_points.txt
collective.groupspace.roles.egg-info/namespace_packages.txt
collective.groupspace.roles.egg-info/not-zip-safe
collective.groupspace.roles.egg-info/paster_plugins.txt
collective.groupspace.roles.egg-info/requires.txt
collective.groupspace.roles.egg-info/top_level.txt
collective/groupspace/__init__.py
collective/groupspace/roles/__init__.py
collective/groupspace/roles/config.py
collective/groupspace/roles/configure.zcml
collective/groupspace/roles/interfaces.py
collective/groupspace/roles/localroles.py
collective/groupspace/roles/browser/__init__.py
collective/groupspace/roles/browser/configure.zcml
collective/groupspace/roles/browser/groupspace_roles.pt
collective/groupspace/roles/browser/kss_roles.py
collective/groupspace/roles/browser/macro_wrapper.pt
collective/groupspace/roles/browser/roles.py
collective/groupspace/roles/locales/collective.groupspace.roles.pot
collective/groupspace/roles/locales/en/LC_MESSAGES/collective.groupspace.roles.po
collective/groupspace/roles/locales/es/LC_MESSAGES/collective.groupspace.roles.po
collective/groupspace/roles/locales/fr/LC_MESSAGES/collective.groupspace.roles.po
collective/groupspace/roles/portlets/__init__.py
collective/groupspace/roles/portlets/configure.zcml
collective/groupspace/roles/portlets/mygroupsportlet.pt
collective/groupspace/roles/portlets/mygroupsportlet.py
collective/groupspace/roles/profiles/default/actions.xml
collective/groupspace/roles/profiles/default/catalog.xml
collective/groupspace/roles/profiles/default/portlets.xml
collective/groupspace/roles/profiles/default/rolemap.xml
collective/groupspace/roles/tests/__init__.py
collective/groupspace/roles/tests/base.py
collective/groupspace/roles/tests/base_mygroupsportlet.py
collective/groupspace/roles/tests/rolespage.txt
collective/groupspace/roles/tests/test_browser_roles.py
collective/groupspace/roles/tests/test_functional.py
collective/groupspace/roles/tests/test_localroles.py
collective/groupspace/roles/tests/test_mygroupsportlet.py
collective/groupspace/roles/tests/test_roles_view.py
collective/groupspace/roles/tests/utils.py